broca/__init__.py
broca-0.0.2.dist-info/METADATA
broca-0.0.2.dist-info/WHEEL
broca-0.0.2.dist-info/RECORD
